LICENSE
MANIFEST.in
README.rst
setup.py
feedreader/__init__.py
feedreader/parser.py
feedreader.egg-info/PKG-INFO
feedreader.egg-info/SOURCES.txt
feedreader.egg-info/dependency_links.txt
feedreader.egg-info/requires.txt
feedreader.egg-info/top_level.txt
feedreader/feeds/__init__.py
feedreader/feeds/atom10.py
feedreader/feeds/rss20.py
feedreader/tests/__init__.py
feedreader/utils/__init__.py
feedreader/utils/dates.py
feedreader/utils/proxy.py