Metadata-Version: 1.0
Name: feedreader
Version: 0.3
Summary: A generic RSS/Atom feedparser.
Home-page: http://github.com/dcramer/feedreader
Author: David Cramer
Author-email: dcramer@gmail.com
License: UNKNOWN
Platform: UNKNOWN
